coingecko_py/__init__.py
coingecko_py/coingecko_py.py
coingecko_py/scripts/github.py
coingecko_py/scripts/swagger.py
coingecko_py/swagger_data/swagger.json
coingecko_py/swagger_data/swagger_processed.json
coingecko_py/swagger_data/swagger_processed_diff.txt
coingecko_py/swagger_data/test_api_calls.json
coingecko_py/swagger_data/test_api_responses.json
coingecko_py/swagger_data/url_to_method.json
coingecko_py/swagger_generated/setup.py
coingecko_py/swagger_generated/swagger_client/__init__.py
coingecko_py/swagger_generated/swagger_client/api/__init__.py
coingecko_py/swagger_generated/swagger_client/api/coingecko_api.py
coingecko_py/swagger_generated/swagger_client/api_client.py
coingecko_py/swagger_generated/swagger_client/configuration.py
coingecko_py/swagger_generated/swagger_client/models/__init__.py
coingecko_py/swagger_generated/swagger_client/rest.py
coingecko_py/utils/__init__.py
coingecko_py/utils/api_meta.py
coingecko_py/utils/constants.py
coingecko_py/utils/utils.py
coingecko_py-1.0.0.dist-info/entry_points.txt
coingecko_py-1.0.0.dist-info/LICENSE
coingecko_py-1.0.0.dist-info/WHEEL
coingecko_py-1.0.0.dist-info/METADATA
coingecko_py-1.0.0.dist-info/RECORD
