Metadata-Version: 2.1
Name: coingecko-py
Version: 1.0.0
Summary: A python API client for the coingecko API.
Home-page: https://github.com/brycemorrow4564/coingecko_py
License: MIT
Author: Bryce Morrow
Author-email: brycemorrow4564@gmail.com
Maintainer: Bryce Morrow
Maintainer-email: brycemorrow4564@gmail.com
Requires-Python: >=3.7,<4.0
Classifier: License :: OSI Approved :: MIT License
Classifier: Programming Language :: Python :: 3
Classifier: Programming Language :: Python :: 3.10
Classifier: Programming Language :: Python :: 3.7
Classifier: Programming Language :: Python :: 3.8
Classifier: Programming Language :: Python :: 3.9
Requires-Dist: certifi (>=2017.4.17,<2018.0.0)
Requires-Dist: python-dotenv (>=0.19.2,<0.20.0)
Requires-Dist: python_dateutil (>=2.5.3,<3.0.0)
Requires-Dist: requests (>=2.27.1,<3.0.0)
Requires-Dist: six (>=1.10,<2.0)
Requires-Dist: urllib3 (>=1.25.10,<2.0.0)
Project-URL: Repository, https://github.com/brycemorrow4564/coingecko_py
